signal_analyser/__init__.py
signal_analyser/analyser.py
signal_analyser-0.1.0.dist-info/METADATA
signal_analyser-0.1.0.dist-info/WHEEL
signal_analyser-0.1.0.dist-info/RECORD
